{
  "db": {
    "name": "db",
    "connector": "memory"
  },


  "gym_app":{
    "host": "35.184.213.125",
    "port": 27017,
    "url": "mongodb://root:teq8FX8v@35.184.213.125:27017",
    "database": "gym_app",
    "password": "teq8FX8v",
    "name": "gym_app",
    "user": "root",
    "connector": "mongodb"
},

  "emailIDs": {
    "name": "emailIDs",
    "connector": "mail",
    "transports": [
      {
        "type": "smtp",
        "host": "smtp.gmail.com",
        "secure": true,
        "port": 465,
        "tls": {
          "rejectUnauthorized": false
        },
        "auth": {
          "user": "appbiometric@gmail.com",
          "pass": "oymyxzyaxokshkpn"
        }
      }
    ]
  }
}
